[
  {
    "id": "rJKAbDd_z",
    "companyId": "HJRa-DOuG",
    "title": "Frontend Developer",
    "description": "We are looking for a Frontend Developer familiar with React."
  },
  {
    "id": "SJRAZDu_z",
    "companyId": "HJRa-DOuG",
    "title": "Backend Developer",
    "description": "We are looking for a Backend Developer familiar with Node.js and Express."
  },
  {
    "id": "rkz1GwOOM",
    "companyId": "SJV0-wdOM",
    "title": "Full-Stack Developer",
    "description": "We are looking for a Full-Stack Developer familiar with Node.js, Express, and React."
  },
  {
    "id": "Bk0C16omI",
    "title": "QA Test Engineer",
    "description": "Senior Test Engineer",
    "companyId": "SJV0-wdOM"
  },
  {
    "id": "HJ6oZ6o7U",
    "title": "QA Test Engineer II",
    "description": "Senior Test Engineer",
    "companyId": "SJV0-wdOM"
  },
  {
    "id": "HkM4NJn7I",
    "companyId": "SJV0-wdOM",
    "title": "UI Developer",
    "description": "New Job"
  },
  {
    "id": "rJLvs1n7I",
    "companyId": "HJRa-DOuG",
    "title": "Intern",
    "description": "Internship for 3 Months"
  },
  {
    "id": "ByS5wQnXL",
    "companyId": "SJV0-wdOM",
    "title": "UI Developer",
    "description": "Summer\n"
  },
  {
    "id": "rk0sK72m8",
    "title": "UI Developer",
    "description": "wadawdaw",
    "companyId": "HJRa-DOuG"
  },
  {
    "id": "ry8rxlpmI",
    "title": "nwe",
    "description": "awdad",
    "companyId": "HJRa-DOuG"
  },
  {
    "id": "H1ptu0lEI",
    "title": "SMA volume by price",
    "description": "awdawdawd",
    "companyId": "HJRa-DOuG"
  },
  {
    "id": "BJ56uAgNU",
    "title": "wadawda",
    "description": "dwadawd",
    "companyId": "HJRa-DOuG"
  },
  {
    "id": "SkL1FAeNU",
    "title": "SMA volume by price",
    "description": "awdawd",
    "companyId": "HJRa-DOuG"
  }
]